rimuru/__init__.py
rimuru/definitions.py
rimuru/exceptions.py
rimuru/core/__init__.py
rimuru/core/decorator.py
rimuru/core/document.py
rimuru/core/generator.py
rimuru/utils/__init__.py
rimuru/utils/handlers.py
rimuru/utils/jinja2/__init__.py
rimuru/utils/jinja2/filters.py
tests/__init__.py
tests/test_api_document_generator.py
tests/test_django_test_client_decorator.py
tests/test_requests_decorator.py
tests/test_service/__init__.py
tests/test_service/flask_/__init__.py
rimuru-0.0.12.dist-info/LICENSE
rimuru-0.0.12.dist-info/METADATA
rimuru-0.0.12.dist-info/WHEEL
rimuru-0.0.12.dist-info/top_level.txt
rimuru-0.0.12.dist-info/RECORD
