Metadata-Version: 2.1
Name: rimuru
Version: 0.0.12
Summary: 📖Use TestCase auto generate API document.
Home-page: https://github.com/TNK-Studio/Rimuru
Author: TNK Studio
Author-email: 741424975@qq.com
License: MIT
Platform: UNKNOWN
Classifier: Programming Language :: Python :: 3
Classifier: License :: OSI Approved :: MIT License
Classifier: Operating System :: OS Independent
Requires-Dist: jinja2
Requires-Dist: werkzeug
